tests/__init__.py
tests/test_api.py
tests/test_roles.py
wg_api_client/__init__.py
wg_api_client/__main__.py
wg_api_client/api.py
wg_api_client/cli.py
wg_api_client/config.py
wg_api_client/helper.py
wg_api_client/unique_id.py
wg_api_client-0.1.9.dist-info/licenses/LICENSE
wg_api_client-0.1.9.dist-info/METADATA
wg_api_client-0.1.9.dist-info/WHEEL
wg_api_client-0.1.9.dist-info/entry_points.txt
wg_api_client-0.1.9.dist-info/top_level.txt
wg_api_client-0.1.9.dist-info/RECORD
